a2woz/__init__.py
a2woz/__main__.py
a2woz/__version__.py
a2woz/a2rchery.py
a2woz/a2rimage.py
a2woz/eddimage.py
a2woz/strings.py
a2woz/wozardry.py
a2woz/loggers/__init__.py
a2woz/loggers/debug.py
a2woz/loggers/default.py
a2woz/loggers/silent.py
a2woz/util/__init__.py
a2woz/util/find.py
a2woz-0.1.0a0.dist-info/LICENSE
a2woz-0.1.0a0.dist-info/METADATA
a2woz-0.1.0a0.dist-info/WHEEL
a2woz-0.1.0a0.dist-info/entry_points.txt
a2woz-0.1.0a0.dist-info/top_level.txt
a2woz-0.1.0a0.dist-info/RECORD
