Metadata-Version: 2.1
Name: a2woz
Version: 0.1.0a0
Summary: Visualize floppy disk flux patterns
Home-page: https://github.com/adafruit/a2woz
Author: Jeff Epler for Adafruit Industries
Author-email: jeff@adafruit.com
License: UNKNOWN
Platform: UNKNOWN
Classifier: Programming Language :: Python :: 3
Classifier: Programming Language :: Python :: 3.9
Classifier: Programming Language :: Python :: 3.10
Classifier: Programming Language :: Python :: Implementation :: CPython
Classifier: License :: OSI Approved :: MIT License
Classifier: Operating System :: OS Independent
Requires-Python: >=3.9
License-File: LICENSE
